{
	"type": "GenericSmelter",
	"name": "Bronzium Forge",
	"description": "Combines Bronze and Steel into Bronzium alloy (Dont't ask)",
	"results" : [
"outputitem" :{"item":"copper","amount":100}
{"item":"lead","amount":100}
]
	"size": 3,
	"hasPower": true,
	"hasLiquids": false,
	"hasItems": true,
	"craftTime": 60,
	"liquidCapacity": 500,
	"itemCapacity": 250,
	"updateEffect": "smeltsmoke",
	"consumes": {
		"power": 0.0,
	},
	"requirements": [
		{ "item": "copper", "amount": 1 },
	],
	"category": "crafting",
	"idleSound": "respawning",
	"research": "steel-forge"
	"idleSoundVolume": 0.5
}
